jyakoTen/__init__.py
jyakoTen/__main__.py
jyakoTen/score.py
jyakoTen/examples/ita04_normal_recitation_result_float32.txt
jyakoTen/examples/ita04_normal_recitation_result_int8.txt
jyakoTen/scores/ita04_normal_recitation_score(321.421 of 324).txt
jyakoTen/transcripts/emotion_transcript_utf8.txt
jyakoTen/transcripts/recitation_transcript_utf8.txt
jyakoTen/transcripts/rohan4600_transcript_utf8.txt
jyakoTen/utils/__init__.py
jyakoTen/utils/alkana_utils.py
jyakoTen/utils/kanji_split.py
jyakoTen/utils/mecab_utils.py
jyakoTen/utils/mora_utils.py
jyakoTen-0.1.0.7.dist-info/LICENSE
jyakoTen-0.1.0.7.dist-info/METADATA
jyakoTen-0.1.0.7.dist-info/WHEEL
jyakoTen-0.1.0.7.dist-info/top_level.txt
jyakoTen-0.1.0.7.dist-info/RECORD
