Metadata-Version: 2.1
Name: jyakoTen
Version: 0.1.0.7
Summary: recognized text scoreing library
License: MIT License
Project-URL: Repository, https://github.com/akjava/jyakoTen
Keywords: tts,stt,rvc,voicechange
Classifier: Development Status :: 3 - Alpha
Classifier: Intended Audience :: Developers
Classifier: Topic :: Multimedia :: Sound/Audio :: Speech
Classifier: License :: OSI Approved :: MIT License
Requires-Python: >=3.10
License-File: LICENSE
Requires-Dist: pyopenjtalk
Requires-Dist: alkana
Requires-Dist: mecab-python3
Requires-Dist: unidic-lite
